easydbjson/__init__.py
easydb_json-1.0.2.dist-info/METADATA
easydb_json-1.0.2.dist-info/WHEEL
easydb_json-1.0.2.dist-info/top_level.txt
easydb_json-1.0.2.dist-info/RECORD
