Metadata-Version: 2.1
Name: easydb-json
Version: 1.0.2
Summary: A simple way to handle database in json.
Home-page: https://github.com/lactua/easydb-json
Author: Lactua
Author-email: lactua@lactua.com
Classifier: Programming Language :: Python :: 3
Classifier: License :: OSI Approved :: MIT License
Classifier: Operating System :: OS Independent
Requires-Python: >=3.6
